persuit-0.1.0.dist-info/METADATA
persuit-0.1.0.dist-info/WHEEL
persuit-0.1.0.dist-info/license_files/LICENSE
persuit/__init__.py
persuit/persuit.cpython-310-x86_64-linux-gnu.so
persuit-0.1.0.dist-info/RECORD
